openai_functionregistry/__init__.py
openai_functionregistry/client.py
openai_functionregistry/generate_pydantic_model.py
openai_functionregistry/tool_registry.py
openai_functionregistry/tool_registry_usage_example.py
openai_functionregistry/utils.py
openai_functionregistry-0.2.10.dist-info/LICENSE
openai_functionregistry-0.2.10.dist-info/METADATA
openai_functionregistry-0.2.10.dist-info/WHEEL
openai_functionregistry-0.2.10.dist-info/RECORD
