Metadata-Version: 2.1
Name: openai_functionregistry
Version: 0.2.10
Summary: OpenAI Function and Parser Registry
Author: Torstein Sørnes
Author-email: t.soernes@gmail.com
Requires-Python: >=3.11,<4.0
Classifier: Programming Language :: Python :: 3
Classifier: Programming Language :: Python :: 3.11
Classifier: Programming Language :: Python :: 3.12
Requires-Dist: betterpathlib (>=0.1.1,<0.2.0)
Requires-Dist: openai (>=1.50.2,<2.0.0)
Requires-Dist: pydantic (>=2.9.2,<3.0.0)
Requires-Dist: python-dotenv (>=1.0.1,<2.0.0)
Requires-Dist: tiktoken (>=0.9.0,<0.10.0)
